evabgp/__init__.py
evabgp/bgp_jnxBgpM2PeerInTotalMessages/__init__.py
evabgp/bgp_jnxBgpM2PeerInTotalMessages/bgp_peer_InTotal_Messages.py
evabgp/bgp_jnxBgpM2PeerState_alert/__init__.py
evabgp/bgp_jnxBgpM2PeerState_alert/bgp_peer_state_monitor.py
evabgp/bgp_jnxBgpM2PeerState_alert/bgp_peer_state_monitor_resolve.py
evabgp/bgp_jnxBgpM2PrefixInPrefixesAccepted_alert/__init__.py
evabgp/bgp_jnxBgpM2PrefixInPrefixesAccepted_alert/bgp_peer_accept_prefixes.py
evabgp/yang_jnxbgp_peer_stateinfo/__init__.py
evabgp/yang_jnxbgp_peer_stateinfo/yang_bgp_peer_info.py
evabgp-0.1.0.dist-info/LICENSE
evabgp-0.1.0.dist-info/METADATA
evabgp-0.1.0.dist-info/WHEEL
evabgp-0.1.0.dist-info/top_level.txt
evabgp-0.1.0.dist-info/RECORD
