Metadata-Version: 2.1
Name: evabgp
Version: 0.1.0
Summary: A Python package for BGP monitoring and state analysis.
Author-email: Your Name <your_email@example.com>
License: MIT
Classifier: Programming Language :: Python :: 3
Classifier: License :: OSI Approved :: MIT License
Classifier: Operating System :: OS Independent
Requires-Python: >=3.7
License-File: LICENSE
Requires-Dist: pysnmp
Requires-Dist: httpx
Requires-Dist: influxdb-client
Requires-Dist: ncclient
Requires-Dist: lxml
